upipe/__init__.py
upipe/__version__.py
upipe/utils.py
upipe/entities/__init__.py
upipe/entities/dataframe.py
upipe/entities/mem_queue.py
upipe/entities/pipe.py
upipe/entities/processor.py
upipe/node/__init__.py
upipe/node/client.py
upipe/node/manager/__init__.py
upipe/node/manager/node_config.py
upipe/node/manager/node_main.py
upipe/node/manager/node_utils.py
upipe/node/manager/pipe_controller.py
upipe/node/manager/process_controller.py
upipe/node/manager/processor_instance.py
upipe/node/server/__init__.py
upipe/node/server/node_controller.py
upipe/node/server/server.py
upipe/node/server/view_api.py
upipe/types/__init__.py
upipe/types/base.py
upipe/types/cloud_q.py
upipe/types/framework.py
upipe/types/http_api.py
upipe/types/mem_queue.py
upipe/types/message_parser.py
upipe/types/messages.py
upipe/types/node.py
upipe/types/performance.py
upipe/types/pipe.py
upipe/types/processor.py
upipe/types/processor_instance.py
upipe/types/schema/__init__.py
upipe/types/schema/schema_generator.py
micropipelines-0.1.8.dist-info/LICENSE
micropipelines-0.1.8.dist-info/METADATA
micropipelines-0.1.8.dist-info/WHEEL
micropipelines-0.1.8.dist-info/top_level.txt
micropipelines-0.1.8.dist-info/RECORD
